raidionicsseg/__init__.py
raidionicsseg/__main__.py
raidionicsseg/fit.py
raidionicsseg/Inference/__init__.py
raidionicsseg/Inference/data_augmentation.py
raidionicsseg/Inference/predictions.py
raidionicsseg/Inference/predictions_classification.py
raidionicsseg/Inference/predictions_reconstruction.py
raidionicsseg/PreProcessing/__init__.py
raidionicsseg/PreProcessing/brain_clipping.py
raidionicsseg/PreProcessing/foreground_selection.py
raidionicsseg/PreProcessing/mediastinum_clipping.py
raidionicsseg/PreProcessing/pre_processing.py
raidionicsseg/Utils/__init__.py
raidionicsseg/Utils/configuration_parser.py
raidionicsseg/Utils/io.py
raidionicsseg/Utils/resample_or_resize.py
raidionicsseg/Utils/volume_utilities.py
raidionicsseg/Utils/Torch/__init__.py
raidionicsseg/Utils/Torch/modules.py
raidionicsseg-1.5.1.dist-info/licenses/LICENSE.md
tests/__init__.py
tests/conftest.py
tests/download_resources.py
raidionicsseg-1.5.1.dist-info/METADATA
raidionicsseg-1.5.1.dist-info/WHEEL
raidionicsseg-1.5.1.dist-info/entry_points.txt
raidionicsseg-1.5.1.dist-info/top_level.txt
raidionicsseg-1.5.1.dist-info/RECORD
