Metadata-Version: 2.4
Name: raidionicsseg
Version: 1.5.1
Summary: Raidionics segmentation and classification back-end with ONNX runtime
Author-email: David Bouget <david.bouget@sintef.no>
License: BSD-2-Clause
Requires-Python: >=3.9
License-File: LICENSE.md
Requires-Dist: nibabel
Requires-Dist: h5py
Requires-Dist: pandas
Requires-Dist: SimpleITK<=2.4.1
Requires-Dist: aenum
Requires-Dist: scikit-image
Requires-Dist: tqdm
Requires-Dist: numpy
Requires-Dist: onnxruntime
Provides-Extra: torch
Requires-Dist: torch>=2.0.0; extra == "torch"
Provides-Extra: ort-gpu
Requires-Dist: onnxruntime-gpu; extra == "ort-gpu"
Dynamic: license-file
